.travis.yml
README.rst
setup.py
tox.ini
mr/__init__.py
mr.awsome.ansible.egg-info/PKG-INFO
mr.awsome.ansible.egg-info/SOURCES.txt
mr.awsome.ansible.egg-info/dependency_links.txt
mr.awsome.ansible.egg-info/entry_points.txt
mr.awsome.ansible.egg-info/namespace_packages.txt
mr.awsome.ansible.egg-info/not-zip-safe
mr.awsome.ansible.egg-info/requires.txt
mr.awsome.ansible.egg-info/top_level.txt
mr/awsome_ansible/__init__.py
mr/awsome_ansible/execnet_connection.py
mr/awsome_ansible/inventory.py
mr/awsome_ansible/remote.py
mr/awsome_ansible/test_ansible.py