Metadata-Version: 1.0
Name: mr.awsome.ansible
Version: 1.0b4
Summary: A plugin for mr.awsome providing integration with Ansible.
Home-page: http://github.com/fschulze/mr.awsome.ansible
Author: Florian Schulze
Author-email: florian.schulze@gmx.net
License: UNKNOWN
Platform: UNKNOWN
